{"nodes": [{"id": "component_appnavbar", "label": "AppNavbar Component", "file_type": "code", "source_file": "components/AppNavbar.tsx", "source_location": null, "source_url": null, "captured_at": null, "author": null, "contributor": null}, {"id": "appnavbar_handleSignOut", "label": "AppNavbar handleSignOut", "file_type": "code", "source_file": "components/AppNavbar.tsx", "source_location": null, "source_url": null, "captured_at": null, "author": null, "contributor": null}], "edges": [{"source": "component_appnavbar", "target": "component_logo", "relation": "references", "confidence": "EXTRACTED", "confidence_score": 1.0, "source_file": "components/AppNavbar.tsx", "source_location": null, "weight": 1.0}, {"source": "component_appnavbar", "target": "api_usage_endpoint", "relation": "calls", "confidence": "EXTRACTED", "confidence_score": 1.0, "source_file": "components/AppNavbar.tsx", "source_location": null, "weight": 1.0}, {"source": "component_appnavbar", "target": "appnavbar_handleSignOut", "relation": "calls", "confidence": "EXTRACTED", "confidence_score": 1.0, "source_file": "components/AppNavbar.tsx", "source_location": null, "weight": 1.0}, {"source": "component_appnavbar", "target": "plan_gating_pattern", "relation": "implements", "confidence": "INFERRED", "confidence_score": 0.75, "source_file": "components/AppNavbar.tsx", "source_location": null, "weight": 1.0}], "hyperedges": []}